bamboo_cli/__init__.py
bamboo_cli/api.py
bamboo_cli/main.py
dw_bamboo_cli-0.0.13.dist-info/METADATA
dw_bamboo_cli-0.0.13.dist-info/WHEEL
dw_bamboo_cli-0.0.13.dist-info/entry_points.txt
dw_bamboo_cli-0.0.13.dist-info/top_level.txt
dw_bamboo_cli-0.0.13.dist-info/RECORD
