Metadata-Version: 2.1
Name: dw-bamboo-cli
Version: 0.0.13
Summary: Command line interface for running Bamboo data pipelines
Home-page: UNKNOWN
Author: Jon Speiser
Author-email: UNKNOWN
License: All Rights Reserved
Platform: UNKNOWN
Requires-Dist: click
Requires-Dist: bamboo-lib
